setup.py
simple_debugger/__init__.py
simple_debugger.egg-info/PKG-INFO
simple_debugger.egg-info/SOURCES.txt
simple_debugger.egg-info/dependency_links.txt
simple_debugger.egg-info/top_level.txt